CHANGES
LICENSE
MANIFEST.in
README.rst
setup.cfg
setup.py
sphinxcontrib/__init__.py
sphinxcontrib/cmd2img.py
sphinxcontrib_cmd2img.egg-info/PKG-INFO
sphinxcontrib_cmd2img.egg-info/SOURCES.txt
sphinxcontrib_cmd2img.egg-info/dependency_links.txt
sphinxcontrib_cmd2img.egg-info/namespace_packages.txt
sphinxcontrib_cmd2img.egg-info/requires.txt
sphinxcontrib_cmd2img.egg-info/top_level.txt