Metadata-Version: 1.0
Name: sphinxcontrib-cmd2img
Version: 1.0.5
Summary: Sphinx extension to render the image by script or command
Home-page: https://github.com/stathissideris/sphinxcontrib-cmd2img
Author: Yongping Guo
Author-email: guoyoooping@163.com
License: BSD
Platform: any
